README.md
setup.py
cpbox/__init__.py
cpbox.egg-info/PKG-INFO
cpbox.egg-info/SOURCES.txt
cpbox.egg-info/dependency_links.txt
cpbox.egg-info/requires.txt
cpbox.egg-info/top_level.txt
cpbox/app/__init__.py
cpbox/app/appconfig.py
cpbox/app/devops.py
cpbox/app/env.py
cpbox/app/eventlog.py
cpbox/app/multiuser.py
cpbox/clis/__init__.py
cpbox/clis/aliyunoss.py
cpbox/clis/mysqlcli.py
cpbox/clis/pipcli.py
cpbox/clis/rediscli.py
cpbox/tool/__init__.py
cpbox/tool/array.py
cpbox/tool/cache.py
cpbox/tool/concurrent.py
cpbox/tool/crontab.py
cpbox/tool/datatypes.py
cpbox/tool/dockerutil.py
cpbox/tool/file.py
cpbox/tool/functocli.py
cpbox/tool/http.py
cpbox/tool/local_cache.py
cpbox/tool/logger.py
cpbox/tool/net.py
cpbox/tool/redistool.py
cpbox/tool/spec.py
cpbox/tool/strings.py
cpbox/tool/strjson.py
cpbox/tool/system.py
cpbox/tool/template.py
cpbox/tool/testutils.py
cpbox/tool/timeutil.py
cpbox/tool/utils.py
tests/__init__.py
tests/test_array.py
tests/test_concurrent.py
tests/test_dockerutil.py
tests/test_eventlog.py
tests/test_file.py
tests/test_functocli.py
tests/test_nameiddict.py
tests/test_net.py
tests/test_strings.py
tests/test_system.py
tests/test_template.py
tests/test_threadpool.py
tests/test_timer.py
tests/test_tool_cache.py
tests/test_tool_redis.py
tests/test_utils.py