Metadata-Version: 2.1
Name: cpbox
Version: 1.5.415
Summary: cp tool box
Home-page: 
Author: https://www.liaohuqiu.com
Author-email: liaohuqiu@gmail.com
Keywords: cpbox
Platform: any
